meizter_ingestion/__init__.py
meizter_ingestion/meizter_ingestion.py
meizter_ingestion-0.0.1.dist-info/LICENSE
meizter_ingestion-0.0.1.dist-info/METADATA
meizter_ingestion-0.0.1.dist-info/WHEEL
meizter_ingestion-0.0.1.dist-info/top_level.txt
meizter_ingestion-0.0.1.dist-info/RECORD
