Metadata-Version: 2.1
Name: meizter_ingestion
Version: 0.0.1
Summary: pacote para manipulação do Dremio
Author: Douglas Borges Martins
Author-email: douglas@meizter.com
License: MIT License
License-File: LICENSE
Requires-Dist: getdaft==0.3.4
Requires-Dist: pyarrow==17.0.0
Requires-Dist: requests==2.32.3
Requires-Dist: ipython
Requires-Dist: python-dotenv
Requires-Dist: pandas==2.2.3
Requires-Dist: numpy==2.1.1
Requires-Dist: fsspec==2023.12.2
Requires-Dist: s3fs==2023.12.2
